simpleemail/__init__.py
simpleemail/message.py
simpleemail/sender.py
simpleemail-0.4.dist-info/LICENSE
simpleemail-0.4.dist-info/METADATA
simpleemail-0.4.dist-info/WHEEL
simpleemail-0.4.dist-info/top_level.txt
simpleemail-0.4.dist-info/RECORD
