Metadata-Version: 2.1
Name: simpleemail
Version: 0.4
Summary: Simple SMTP wrapper for Python's SMTP, supports both HTML and text based emails. Now supports attachments!
Home-page: https://github.com/N-C-C/SimpleEmail
Author: John Glasgow
Author-email: jglasgow@northampton.edu
License: MIT
Platform: UNKNOWN
Classifier: Development Status :: 3 - Alpha
Classifier: Topic :: Communications :: Email
Classifier: License :: OSI Approved :: MIT License
Classifier: Programming Language :: Python :: 3.5
Classifier: Programming Language :: Python :: 3.6
Classifier: Programming Language :: Python :: 3.5
Classifier: Programming Language :: Python :: 3.7
Classifier: Programming Language :: Python :: Implementation :: CPython
